LICENSE
MANIFEST.in
README.rst
setup.py
tastypie_spore_docs/__init__.py
tastypie_spore_docs/direct_template_view.py
tastypie_spore_docs/models.py
tastypie_spore_docs/tests.py
tastypie_spore_docs/urls.py
tastypie_spore_docs/views.py
tastypie_spore_docs.egg-info/PKG-INFO
tastypie_spore_docs.egg-info/SOURCES.txt
tastypie_spore_docs.egg-info/dependency_links.txt
tastypie_spore_docs.egg-info/not-zip-safe
tastypie_spore_docs.egg-info/requires.txt
tastypie_spore_docs.egg-info/top_level.txt
tastypie_spore_docs/static/css/bootstrap-combined.min.css
tastypie_spore_docs/static/css/bootstrap-combined.min.css~
tastypie_spore_docs/static/css/docs.css
tastypie_spore_docs/static/css/docs.css~
tastypie_spore_docs/static/css/zenburn.min.css
tastypie_spore_docs/static/img/ajax-loader.gif
tastypie_spore_docs/static/img/favicon.ico
tastypie_spore_docs/static/img/favicon.png
tastypie_spore_docs/static/img/glyphicons-halflings-white.png
tastypie_spore_docs/static/img/glyphicons-halflings.png
tastypie_spore_docs/static/js/ZeroClipboard.js
tastypie_spore_docs/static/js/bootstrap.min.js
tastypie_spore_docs/static/js/canvasmol.js
tastypie_spore_docs/static/js/fileinput.jquery.js
tastypie_spore_docs/static/js/highlight.min.js
tastypie_spore_docs/static/js/jquery-1.9.1.min.js
tastypie_spore_docs/static/js/jquery-migrate-1.2.0.min.js
tastypie_spore_docs/static/js/jquery-ui-1.8.custom.min.js
tastypie_spore_docs/static/js/jquery.base64.js
tastypie_spore_docs/static/js/jquery.mousewheel.js
tastypie_spore_docs/static/js/markdown.min.js
tastypie_spore_docs/static/js/raphael.min.js
tastypie_spore_docs/static/js/spore.js
tastypie_spore_docs/static/js/spore.js~
tastypie_spore_docs/static/js/vkbeautify.js
tastypie_spore_docs/static/swf/ZeroClipboard.swf
tastypie_spore_docs/templates/docs.html
tastypie_spore_docs/templates/head_banner.html