Metadata-Version: 1.1
Name: tastypie-spore-docs
Version: 0.1.2
Summary: This Django app generates SPORE endpoint from Tastypie REST API and provides a JavaScript based SPORE client.
Home-page: https://www.ebi.ac.uk/chembldb/index.php/ws
Author: Michal Nowotka
Author-email: mnowotka@ebi.ac.uk
License: Apache Software License
Platform: UNKNOWN
Classifier: Development Status :: 2 - Pre-Alpha
Classifier: Environment :: Web Environment
Classifier: Framework :: Django
Classifier: Intended Audience :: Developers
Classifier: License :: OSI Approved :: Apache Software License
Classifier: Operating System :: POSIX :: Linux
Classifier: Programming Language :: Python :: 2.7
Classifier: Topic :: Software Development :: Documentation
